micro_metrics/__init__.py
micro_metrics/bp/__init__.py
micro_metrics/bp/orchestrator.py
micro_metrics/dmo/__init__.py
micro_metrics/dmo/metric_cc_counter.py
micro_metrics/dmo/metric_fp_counter.py
micro_metrics/dmo/metric_import_counter.py
micro_metrics/dmo/metric_loc_counter.py
micro_metrics/dmo/metric_tloc_counter.py
micro_metrics/router.py
micro_metrics/svc/__init__.py
micro_metrics/svc/compute_complexity.py
micro_metrics/svc/find_file_metrics.py
micro_metrics/svc/find_folder_metrics.py
micro_metrics/svc/read_file_content.py
micro_metrics-0.1.4.dist-info/WHEEL
micro_metrics-0.1.4.dist-info/METADATA
micro_metrics-0.1.4.dist-info/RECORD
